kuyruk/__init__.py
kuyruk/__main__.py
kuyruk/config.py
kuyruk/connection.py
kuyruk/exceptions.py
kuyruk/heartbeat.py
kuyruk/importer.py
kuyruk/kuyruk.py
kuyruk/result.py
kuyruk/signals.py
kuyruk/task.py
kuyruk/worker.py
kuyruk-10.2.1.dist-info/licenses/LICENSE
kuyruk-10.2.1.dist-info/METADATA
kuyruk-10.2.1.dist-info/WHEEL
kuyruk-10.2.1.dist-info/entry_points.txt
kuyruk-10.2.1.dist-info/top_level.txt
kuyruk-10.2.1.dist-info/zip-safe
kuyruk-10.2.1.dist-info/RECORD
