Metadata-Version: 2.4
Name: Kuyruk
Version: 10.2.1
Summary: Simple task queue
Home-page: https://github.com/cenkalti/kuyruk
Author: Cenk Altı
Author-email: cenkalti@gmail.com
Keywords: rabbitmq distributed task queue
Classifier: Development Status :: 5 - Production/Stable
Classifier: Intended Audience :: Developers
Classifier: License :: OSI Approved :: MIT License
Classifier: Operating System :: OS Independent
Classifier: Programming Language :: Python
Classifier: Programming Language :: Python :: 3.10
Classifier: Topic :: Software Development :: Object Brokering
Classifier: Topic :: System :: Distributed Computing
License-File: LICENSE
Requires-Dist: amqp>=2
Requires-Dist: blinker>=1.3
Requires-Dist: monotonic>=1.6
Dynamic: author
Dynamic: author-email
Dynamic: classifier
Dynamic: description
Dynamic: home-page
Dynamic: keywords
Dynamic: license-file
Dynamic: requires-dist
Dynamic: summary
